src/__init__.py
src/Datasets/irisdata.py
src/Neural_Networks/HiddenLayerNN.py
src/Neural_Networks/SingleLayerNN.py
snupy-1.0.3.dist-info/METADATA
snupy-1.0.3.dist-info/WHEEL
snupy-1.0.3.dist-info/licenses/LICENSE
snupy-1.0.3.dist-info/RECORD
