Metadata-Version: 2.1
Name: SNUPy
Version: 1.0.3
Summary: Python Package for Machine Learning
Project-URL: Homepage, https://github.com/Rohan-s18/SNUPy
Author-email: Rohan Singh <rohan.b.singh@gmail.com>
License-File: LICENSE
Classifier: License :: OSI Approved :: MIT License
Classifier: Operating System :: OS Independent
Classifier: Programming Language :: Python :: 3
Requires-Python: >=3.7
